[{"buildOrder":12,"reportUrl":"https://frontend-park-mail-ru.github.io/2025_2_DavaiDavaiDeploy/12","reportName":"Allure Report with history","data":{"Product defects":3,"Test defects":2}},{"buildOrder":12,"reportUrl":"https://frontend-park-mail-ru.github.io/2025_2_DavaiDavaiDeploy/12","reportName":"Allure Report with history","data":{"Product defects":3,"Test defects":2}},{"buildOrder":12,"reportUrl":"https://frontend-park-mail-ru.github.io/2025_2_DavaiDavaiDeploy/12","reportName":"Allure Report with history","data":{"Product defects":3,"Test defects":2}},{"buildOrder":10,"reportUrl":"https://frontend-park-mail-ru.github.io/2025_2_DavaiDavaiDeploy/10","reportName":"Allure Report with history","data":{}},{"buildOrder":9,"reportUrl":"https://frontend-park-mail-ru.github.io/2025_2_DavaiDavaiDeploy/9","reportName":"Allure Report with history","data":{"Product defects":3,"Test defects":2}},{"buildOrder":4,"reportUrl":"https://frontend-park-mail-ru.github.io/2025_2_DavaiDavaiDeploy/4","reportName":"Allure Report with history","data":{}},{"buildOrder":3,"reportUrl":"https://frontend-park-mail-ru.github.io/2025_2_DavaiDavaiDeploy/3","reportName":"Allure Report with history","data":{}},{"buildOrder":8,"reportUrl":"https://frontend-park-mail-ru.github.io/2025_2_DavaiDavaiDeploy/8","reportName":"Allure Report with history","data":{}},{"buildOrder":8,"reportUrl":"https://frontend-park-mail-ru.github.io/2025_2_DavaiDavaiDeploy/8","reportName":"Allure Report with history","data":{"Test defects":5}},{"data":{}}]